mdahole2/__init__.py
mdahole2/analysis/__init__.py
mdahole2/analysis/hole.py
mdahole2/analysis/templates.py
mdahole2/analysis/utils.py
mdahole2/data/README.md
mdahole2/data/__init__.py
mdahole2/data/files.py
mdahole2/data/mda.txt
mdahole2/tests/__init__.py
mdahole2/tests/conftest.py
mdahole2/tests/datafiles.py
mdahole2/tests/test_duecredit.py
mdahole2/tests/test_mdakithole2.py
mdahole2/tests/utils.py
mdahole2/tests/data/1grm_elNemo_mode7.pdb.bz2
mdahole2/tests/data/1grm_single.pdb
mdahole2/tests/data/adk_dims.dcd
mdahole2-0.4.0.dist-info/AUTHORS.md
mdahole2-0.4.0.dist-info/LICENSE
mdahole2-0.4.0.dist-info/METADATA
mdahole2-0.4.0.dist-info/WHEEL
mdahole2-0.4.0.dist-info/top_level.txt
mdahole2-0.4.0.dist-info/RECORD
