Metadata-Version: 2.1
Name: mdahole2
Version: 0.4.0
Summary: A Python interface for the HOLE suite tools to analyze an ion channel pore or transporter pathway as a function of time or arbitrary order parameters.
Author-email: MDAnalysis <mdanalysis@numfocus.org>
Maintainer-email: MDAnalysis <mdanalysis@numfocus.org>
License: GNU GENERAL PUBLIC LICENSE
Project-URL: source, https://github.com/MDAnalysis/mdahole2
Project-URL: documentation, https://www.mdanalysis.org/mdahole2/
Keywords: molecular simulations,molecular dynamics,ion channel,transporter pathway
Classifier: Development Status :: 6 - Mature
Classifier: Environment :: Console
Classifier: Intended Audience :: Science/Research
Classifier: License :: OSI Approved :: GNU General Public License v2 or later (GPLv2+)
Classifier: Programming Language :: C
Classifier: Programming Language :: Python
Classifier: Programming Language :: Python :: 3.9
Classifier: Programming Language :: Python :: 3.10
Classifier: Programming Language :: Python :: 3.11
Classifier: Programming Language :: Python :: 3.12
Classifier: Topic :: Scientific/Engineering
Classifier: Topic :: Software Development :: Libraries :: Python Modules
Requires-Python: >=3.9
License-File: LICENSE
License-File: AUTHORS.md
Requires-Dist: MDAnalysis >=2.0.0
Provides-Extra: doc
Requires-Dist: sphinx ; extra == 'doc'
Requires-Dist: sphinx-rtd-theme ; extra == 'doc'
Provides-Extra: test
Requires-Dist: pytest >=6.0 ; extra == 'test'
Requires-Dist: pytest-xdist >=2.5 ; extra == 'test'
Requires-Dist: pytest-cov >=3.0 ; extra == 'test'
